Metadata-Version: 2.1
Name: sight
Version: 0.1.1
Summary: A library for Vision Processing
Home-page: http://github.com/adam-mcdaniel/small-vision
Author: Adam McDaniel
Author-email: adam.mcdaniel17@gmail.com
License: Apache-2.0
Platform: UNKNOWN
Classifier: Development Status :: 3 - Alpha
Classifier: Intended Audience :: Developers
Classifier: Programming Language :: Python :: 3
